organizeit2/__init__.py
organizeit2/cli.py
organizeit2/core.py
organizeit2/fsspec_types.py
organizeit2/types.py
organizeit2/tests/conftest.py
organizeit2/tests/test_backends.py
organizeit2/tests/test_cli.py
organizeit2/tests/test_core.py
organizeit2/tests/test_fsspec_types.py
organizeit2/tests/test_regressions.py
organizeit2/tests/test_types.py
organizeit2/tests/directory/subdir1/file1
organizeit2/tests/directory/subdir1/file1.md
organizeit2/tests/directory/subdir1/file1.png
organizeit2/tests/directory/subdir1/file1.txt
organizeit2/tests/directory/subdir1/file2
organizeit2/tests/directory/subdir1/file2.md
organizeit2/tests/directory/subdir1/file2.png
organizeit2/tests/directory/subdir1/file2.txt
organizeit2/tests/directory/subdir1/subsubdir1/file1
organizeit2/tests/directory/subdir1/subsubdir1/file1.md
organizeit2/tests/directory/subdir1/subsubdir1/file1.png
organizeit2/tests/directory/subdir1/subsubdir1/file1.txt
organizeit2/tests/directory/subdir1/subsubdir1/file2
organizeit2/tests/directory/subdir1/subsubdir1/file2.md
organizeit2/tests/directory/subdir1/subsubdir1/file2.png
organizeit2/tests/directory/subdir1/subsubdir1/file2.txt
organizeit2/tests/directory/subdir1/subsubdir2/file1
organizeit2/tests/directory/subdir1/subsubdir2/file1.md
organizeit2/tests/directory/subdir1/subsubdir2/file1.png
organizeit2/tests/directory/subdir1/subsubdir2/file1.txt
organizeit2/tests/directory/subdir1/subsubdir2/file2
organizeit2/tests/directory/subdir1/subsubdir2/file2.md
organizeit2/tests/directory/subdir1/subsubdir2/file2.png
organizeit2/tests/directory/subdir1/subsubdir2/file2.txt
organizeit2/tests/directory/subdir2/file1
organizeit2/tests/directory/subdir2/file1.md
organizeit2/tests/directory/subdir2/file1.png
organizeit2/tests/directory/subdir2/file1.txt
organizeit2/tests/directory/subdir2/file2
organizeit2/tests/directory/subdir2/file2.md
organizeit2/tests/directory/subdir2/file2.png
organizeit2/tests/directory/subdir2/file2.txt
organizeit2-0.7.2.dist-info/METADATA
organizeit2-0.7.2.dist-info/WHEEL
organizeit2-0.7.2.dist-info/entry_points.txt
organizeit2-0.7.2.dist-info/licenses/LICENSE
organizeit2-0.7.2.dist-info/RECORD
