Metadata-Version: 2.4
Name: organizeit2
Version: 0.7.2
Summary: Engage with Zorp!
Project-URL: Repository, https://github.com/1kbgz/organizeit2
Project-URL: Homepage, https://github.com/1kbgz/organizeit2
Author-email: the organizeit2 authors <t.paine154@gmail.com>
License: Apache-2.0
License-File: LICENSE
Keywords: filesystem,pydantic
Classifier: Development Status :: 3 - Alpha
Classifier: Programming Language :: Python
Classifier: Programming Language :: Python :: 3
Classifier: Programming Language :: Python :: 3.9
Classifier: Programming Language :: Python :: 3.10
Classifier: Programming Language :: Python :: 3.11
Classifier: Programming Language :: Python :: 3.12
Classifier: Programming Language :: Python :: 3.13
Classifier: Programming Language :: Python :: Implementation :: CPython
Classifier: Programming Language :: Python :: Implementation :: PyPy
Requires-Python: >=3.9
Requires-Dist: ccflow
Requires-Dist: fsspec
Provides-Extra: cli
Requires-Dist: rich; extra == 'cli'
Requires-Dist: typer; extra == 'cli'
Provides-Extra: develop
Requires-Dist: build; extra == 'develop'
Requires-Dist: bump-my-version; extra == 'develop'
Requires-Dist: check-manifest; extra == 'develop'
Requires-Dist: hatchling; extra == 'develop'
Requires-Dist: pytest; extra == 'develop'
Requires-Dist: pytest-cov; extra == 'develop'
Requires-Dist: rich; extra == 'develop'
Requires-Dist: ruff; extra == 'develop'
Requires-Dist: s3fs; extra == 'develop'
Requires-Dist: twine; extra == 'develop'
Requires-Dist: typer; extra == 'develop'
Requires-Dist: uv; extra == 'develop'
Requires-Dist: wheel; extra == 'develop'
